{
  "friend1" : {
    "friendUid" : "Ei0vOns94NR6JgDQG04NANrZHII3",
    "isAccepted" : true,
    "isPending" : false,
    "uid" : "77777"
  },
  "friend2" : {
    "friendUid" : "88888",
    "isAccepted" : false,
    "isPending" : true,
    "uid" : "Ei0vOns94NR6JgDQG04NANrZHII3"
  },
  "friend3" : {
    "friendUid" : "0000000",
    "isAccepted" : true,
    "isPending" : false,
    "uid" : "Ei0vOns94NR6JgDQG04NANrZHII3"
  },
  "friend4" : {
    "friendUid" : "99999",
    "isAccepted" : false,
    "isPending" : true,
    "uid" : "12345"
  }
}